[{"title":"Mikrotik Access Point","endpoint":"http://192.168.233.1","timestamp":1533502109670154195,"times":[{"rtt":7162223}],"healthy":true},{"title":"Odoo","endpoint":"http://10.5.0.2:8069","timestamp":1533502109668895291,"times":[{"rtt":61810011}],"healthy":true},{"title":"PosBox","endpoint":"http://10.5.0.3:8069","timestamp":1533502109668927270,"times":[{"rtt":70985874}],"healthy":true},{"title":"Printer 1","endpoint":"192.168.233.3:80","timestamp":1533502109670143830,"times":[{"rtt":33337838}],"healthy":true},{"title":"Printer 2","endpoint":"192.168.233.5:80","timestamp":1533502109668937531,"times":[{"rtt":34219138}],"healthy":true},{"title":"PoS Tablet","endpoint":"192.168.233.49:8080","timestamp":1533502109677765687,"times":[{"rtt":251696438}],"healthy":true}]