[{"title":"Mikrotik Access Point","endpoint":"http://192.168.233.1","timestamp":1533550109668789858,"times":[{"rtt":7642122}],"healthy":true},{"title":"Odoo","endpoint":"http://10.5.0.2:8069","timestamp":1533550109668864233,"times":[{"rtt":67312850}],"healthy":true},{"title":"PosBox","endpoint":"http://10.5.0.3:8069","timestamp":1533550109668830222,"times":[{"rtt":71708259}],"healthy":true},{"title":"Printer 1","endpoint":"192.168.233.3:80","timestamp":1533550109669549075,"times":[{"rtt":32573433}],"healthy":true},{"title":"Printer 2","endpoint":"192.168.233.5:80","timestamp":1533550109668780952,"times":[{"rtt":33638743}],"healthy":true},{"title":"PoS Tablet","endpoint":"192.168.233.49:8080","timestamp":1533550109676996770,"times":[{"rtt":242397646}],"healthy":true}]